sideload_nu_0_bin_6633e8c7e41b4d34e4edde78/__init__.py
sideload_nu_0_bin_6633e8c7e41b4d34e4edde78/nu-0.93.0-x86_64-pc-windows-msvc.zip
sideload_nu_0_bin_6633e8c7e41b4d34e4edde78-1.0.0.dist-info/METADATA
sideload_nu_0_bin_6633e8c7e41b4d34e4edde78-1.0.0.dist-info/WHEEL
sideload_nu_0_bin_6633e8c7e41b4d34e4edde78-1.0.0.dist-info/top_level.txt
sideload_nu_0_bin_6633e8c7e41b4d34e4edde78-1.0.0.dist-info/RECORD
