Metadata-Version: 2.1
Name: sideload_nu_0_bin_6633e8c7e41b4d34e4edde78
Version: 1.0.0
Summary: Sideloaded package
Author: Null Void
Requires-Python: >=3.8
